{
  "please_wait": "Пожалуйста, подождите…",
  "map.mods.heist": "кража",
  "map.mods.outdated": "устарело",
  "Support development on": "Поддержите разработку на",
  "updates.maybe_outdated": "У вас может быть устаревшая версия",
  "updates.latest": "У вас самая последняя версия",
  "updates.error": "Ошибка при проверке наличия обновлений",
  "updates.checking": "Проверка наличия обновлений",
  "updates.downloading": "Скачивание…",
  "updates.available": "Доступно обновление: {0}",
  "updates.never_checked": "Последняя проверка: никогда",
  "updates.last_checked": "Последняя проверка: {0}",
  "updates.check_now": "Проверить сейчас",
  "updates.install_now": "Установить сейчас",
  "updates.downloads_page": "Открыть страницу скачивания",
  "updates.installed_on_exit": "Оно будет установлено автоматически при выходе",
  "updates.download_manually": "Вы можете загрузить его с GitHub",
  "updates.download_disabled": "Вы отключили автоматическую загрузку обновлений"
}